spider/__init__.py
spider/async_spider.py
spider/spider.py
spider/spider.pyi
spider/spider_types.py
spider_client-0.1.84.dist-info/licenses/LICENSE
spider_client-0.1.84.dist-info/METADATA
spider_client-0.1.84.dist-info/WHEEL
spider_client-0.1.84.dist-info/top_level.txt
spider_client-0.1.84.dist-info/RECORD
